{ 
	 "images": [ 
{
	 "categoryid": "0", "uri": "savingImages/ios/airSeat.jpg" 
},
{
	 "categoryid": "0", "uri": "savingImages/ios/airView.jpg" 
},
{
	 "categoryid": "0", "uri": "savingImages/ios/alFresco.jpg" 
},
{
	 "categoryid": "0", "uri": "savingImages/ios/allergiesMuch.jpg" 
},
{
	 "categoryid": "0", "uri": "savingImages/ios/alley.jpg" 
},
{
	 "categoryid": "0", "uri": "savingImages/ios/asiaTraffic.jpg" 
},
{
	 "categoryid": "0", "uri": "savingImages/ios/bakerBeach.jpg" 
},
{
	 "categoryid": "0", "uri": "savingImages/ios/barcelonaTraffic.jpg" 
},
{
	 "categoryid": "0", "uri": "savingImages/ios/beach.jpg" 
},
{
	 "categoryid": "0", "uri": "savingImages/ios/beachBus.jpg" 
},
{
	 "categoryid": "0", "uri": "savingImages/ios/beachGrass.jpg" 
},
{
	 "categoryid": "0", "uri": "savingImages/ios/beachWalk.jpg" 
},
{
	 "categoryid": "0", "uri": "savingImages/ios/bootPath.jpg" 
},
{
	 "categoryid": "0", "uri": "savingImages/ios/brick.jpg" 
},
{
	 "categoryid": "0", "uri": "savingImages/ios/brightStreet.jpg" 
},
{
	 "categoryid": "0", "uri": "savingImages/ios/bwBridge.jpg" 
},
{
	 "categoryid": "0", "uri": "savingImages/ios/campFire.jpg" 
},
{
	 "categoryid": "0", "uri": "savingImages/ios/canal.jpg" 
},
{
	 "categoryid": "0", "uri": "savingImages/ios/canalTurn.jpg" 
},
{
	 "categoryid": "0", "uri": "savingImages/ios/canoe.jpg" 
},
{
	 "categoryid": "0", "uri": "savingImages/ios/carmel.jpg" 
},
{
	 "categoryid": "0", "uri": "savingImages/ios/castle.jpg" 
},
{
	 "categoryid": "0", "uri": "savingImages/ios/chairlift.jpg" 
},
{
	 "categoryid": "0", "uri": "savingImages/ios/cherry.jpg" 
},
{
	 "categoryid": "0", "uri": "savingImages/ios/chicago.jpg" 
},
{
	 "categoryid": "0", "uri": "savingImages/ios/citrus.jpg" 
},
{
	 "categoryid": "0", "uri": "savingImages/ios/city.jpg" 
},
{
	 "categoryid": "0", "uri": "savingImages/ios/cityConference.jpg" 
},
{
	 "categoryid": "0", "uri": "savingImages/ios/cityOnAHill.jpg" 
},
{
	 "categoryid": "0", "uri": "savingImages/ios/citySpires.jpg" 
},
{
	 "categoryid": "0", "uri": "savingImages/ios/clayPaintPots.jpg" 
},
{
	 "categoryid": "0", "uri": "savingImages/ios/clockVintage.jpg" 
},
{
	 "categoryid": "0", "uri": "savingImages/ios/cloudRunner.jpg" 
},
{
	 "categoryid": "0", "uri": "savingImages/ios/coffeeBeansArtfullyArranged.jpg" 
},
{
	 "categoryid": "0", "uri": "savingImages/ios/coffeeBellReceipt.jpg" 
},
{
	 "categoryid": "0", "uri": "savingImages/ios/coffeeTable.jpg" 
},
{
	 "categoryid": "0", "uri": "savingImages/ios/coldLakeReflection.jpg" 
},
{
	 "categoryid": "0", "uri": "savingImages/ios/concert.jpg" 
},
{
	 "categoryid": "0", "uri": "savingImages/ios/coupleSitting.jpg" 
},
{
	 "categoryid": "0", "uri": "savingImages/ios/cupFullOfRasberries.jpg" 
},
{
	 "categoryid": "0", "uri": "savingImages/ios/czechRepublic.jpg" 
},
{
	 "categoryid": "0", "uri": "savingImages/ios/dandelionSunset.jpg" 
},
{
	 "categoryid": "0", "uri": "savingImages/ios/darkForest.jpg" 
},
{
	 "categoryid": "0", "uri": "savingImages/ios/daylightBicycleNewspaper.jpg" 
},
{
	 "categoryid": "0", "uri": "savingImages/ios/delta.jpg" 
},
{
	 "categoryid": "0", "uri": "savingImages/ios/dirtRoad.jpg" 
},
{
	 "categoryid": "0", "uri": "savingImages/ios/dreamcatcher.jpg" 
},
{
	 "categoryid": "0", "uri": "savingImages/ios/dunebuggy.jpg" 
},
{
	 "categoryid": "0", "uri": "savingImages/ios/dunes.jpg" 
},
{
	 "categoryid": "0", "uri": "savingImages/ios/eastRiverLookingNorth.jpg" 
},
{
	 "categoryid": "0", "uri": "savingImages/ios/elevatedRail.jpg" 
},
{
	 "categoryid": "0", "uri": "savingImages/ios/empireStateView.jpg" 
},
{
	 "categoryid": "0", "uri": "savingImages/ios/euroBiking.jpg" 
},
{
	 "categoryid": "0", "uri": "savingImages/ios/eveningTower.jpg" 
},
{
	 "categoryid": "0", "uri": "savingImages/ios/everest.jpg" 
},
{
	 "categoryid": "0", "uri": "savingImages/ios/falls.jpg" 
},
{
	 "categoryid": "0", "uri": "savingImages/ios/family.jpg" 
},
{
	 "categoryid": "0", "uri": "savingImages/ios/fenceIvy.jpg" 
},
{
	 "categoryid": "0", "uri": "savingImages/ios/ferry.jpg" 
},
{
	 "categoryid": "0", "uri": "savingImages/ios/fields.jpg" 
},
{
	 "categoryid": "0", "uri": "savingImages/ios/fish.jpg" 
},
{
	 "categoryid": "0", "uri": "savingImages/ios/fjiordBay.jpg" 
},
{
	 "categoryid": "0", "uri": "savingImages/ios/flightFormation.jpg" 
},
{
	 "categoryid": "0", "uri": "savingImages/ios/flower.jpg" 
},
{
	 "categoryid": "0", "uri": "savingImages/ios/fogHill.jpg" 
},
{
	 "categoryid": "0", "uri": "savingImages/ios/fogRidgeCityValley.jpg" 
},
{
	 "categoryid": "0", "uri": "savingImages/ios/foreignTraffic.jpg" 
},
{
	 "categoryid": "0", "uri": "savingImages/ios/glisten.jpg" 
},
{
	 "categoryid": "0", "uri": "savingImages/ios/grassPines.jpg" 
},
{
	 "categoryid": "0", "uri": "savingImages/ios/grassSea.jpg" 
},
{
	 "categoryid": "0", "uri": "savingImages/ios/greenDew.jpg" 
},
{
	 "categoryid": "0", "uri": "savingImages/ios/greyBeach.jpg" 
},
{
	 "categoryid": "0", "uri": "savingImages/ios/greyRoad.jpg" 
},
{
	 "categoryid": "0", "uri": "savingImages/ios/heli.jpg" 
},
{
	 "categoryid": "0", "uri": "savingImages/ios/heronBoat.jpg" 
},
{
	 "categoryid": "0", "uri": "savingImages/ios/hike.jpg" 
},
{
	 "categoryid": "0", "uri": "savingImages/ios/ireland.jpg" 
},
{
	 "categoryid": "0", "uri": "savingImages/ios/jetSky.jpg" 
},
{
	 "categoryid": "0", "uri": "savingImages/ios/jog.jpg" 
},
{
	 "categoryid": "0", "uri": "savingImages/ios/koPhi.jpg" 
},
{
	 "categoryid": "0", "uri": "savingImages/ios/leaf.jpg" 
},
{
	 "categoryid": "0", "uri": "savingImages/ios/leafDeck.jpg" 
},
{
	 "categoryid": "0", "uri": "savingImages/ios/leap.jpg" 
},
{
	 "categoryid": "0", "uri": "savingImages/ios/lifeBuoy.jpg" 
},
{
	 "categoryid": "0", "uri": "savingImages/ios/lifeguardStation.jpg" 
},
{
	 "categoryid": "0", "uri": "savingImages/ios/lightning.jpg" 
},
{
	 "categoryid": "0", "uri": "savingImages/ios/littleForestShed.jpg" 
},
{
	 "categoryid": "0", "uri": "savingImages/ios/litUpStreet.jpg" 
},
{
	 "categoryid": "0", "uri": "savingImages/ios/lonelyField.jpg" 
},
{
	 "categoryid": "0", "uri": "savingImages/ios/long-road-ahead.jpg" 
},
{
	 "categoryid": "0", "uri": "savingImages/ios/lookUp.jpg" 
},
{
	 "categoryid": "0", "uri": "savingImages/ios/lotus.jpg" 
},
{
	 "categoryid": "0", "uri": "savingImages/ios/malibuPierSurf.jpg" 
},
{
	 "categoryid": "0", "uri": "savingImages/ios/manor.jpg" 
},
{
	 "categoryid": "0", "uri": "savingImages/ios/mistyCliff.jpg" 
},
{
	 "categoryid": "0", "uri": "savingImages/ios/mountainPath.jpg" 
},
{
	 "categoryid": "0", "uri": "savingImages/ios/moutain.jpg" 
},
{
	 "categoryid": "0", "uri": "savingImages/ios/newportYachts.jpg" 
},
{
	 "categoryid": "0", "uri": "savingImages/ios/nuevaYork.jpg" 
},
{
	 "categoryid": "0", "uri": "savingImages/ios/nycTaxi.jpg" 
},
{
	 "categoryid": "0", "uri": "savingImages/ios/palmCentralSway.jpg" 
},
{
	 "categoryid": "0", "uri": "savingImages/ios/palmSprings.jpg" 
},
{
	 "categoryid": "0", "uri": "savingImages/ios/Paradise.jpg" 
},
{
	 "categoryid": "0", "uri": "savingImages/ios/pathToBeach.jpg" 
},
{
	 "categoryid": "0", "uri": "savingImages/ios/pelicanDock.jpg" 
},
{
	 "categoryid": "0", "uri": "savingImages/ios/pineLake.jpg" 
},
{
	 "categoryid": "0", "uri": "savingImages/ios/plains.jpg" 
},
{
	 "categoryid": "0", "uri": "savingImages/ios/planeView.jpg" 
},
{
	 "categoryid": "0", "uri": "savingImages/ios/poolLeap.jpg" 
},
{
	 "categoryid": "0", "uri": "savingImages/ios/powerTree.jpg" 
},
{
	 "categoryid": "0", "uri": "savingImages/ios/prick.jpg" 
},
{
	 "categoryid": "0", "uri": "savingImages/ios/puppies.jpg" 
},
{
	 "categoryid": "0", "uri": "savingImages/ios/railwayBeach.jpg" 
},
{
	 "categoryid": "0", "uri": "savingImages/ios/range.jpg" 
},
{
	 "categoryid": "0", "uri": "savingImages/ios/ridge.jpg" 
},
{
	 "categoryid": "0", "uri": "savingImages/ios/rockBeach.jpg" 
},
{
	 "categoryid": "0", "uri": "savingImages/ios/rocks.jpg" 
},
{
	 "categoryid": "0", "uri": "savingImages/ios/rockWavesCrashing.jpg" 
},
{
	 "categoryid": "0", "uri": "savingImages/ios/ruggedCoast.jpg" 
},
{
	 "categoryid": "0", "uri": "savingImages/ios/sandyHand.jpg" 
},
{
	 "categoryid": "0", "uri": "savingImages/ios/santaMonicaBluffs.jpg" 
},
{
	 "categoryid": "0", "uri": "savingImages/ios/santaMonicaPalm.jpg" 
},
{
	 "categoryid": "0", "uri": "savingImages/ios/santaMonicaWaveBreak.jpg" 
},
{
	 "categoryid": "0", "uri": "savingImages/ios/sequoiaGiants.jpg" 
},
{
	 "categoryid": "0", "uri": "savingImages/ios/sequoiaSnow.jpg" 
},
{
	 "categoryid": "0", "uri": "savingImages/ios/shanghai.jpg" 
},
{
	 "categoryid": "0", "uri": "savingImages/ios/sheep.jpg" 
},
{
	 "categoryid": "0", "uri": "savingImages/ios/skatepark.jpg" 
},
{
	 "categoryid": "0", "uri": "savingImages/ios/skyRose.jpg" 
},
{
	 "categoryid": "0", "uri": "savingImages/ios/snowGrass.jpg" 
},
{
	 "categoryid": "0", "uri": "savingImages/ios/sparklerHands.jpg" 
},
{
	 "categoryid": "0", "uri": "savingImages/ios/stairs.jpg" 
},
{
	 "categoryid": "0", "uri": "savingImages/ios/starlightFence.jpg" 
},
{
	 "categoryid": "0", "uri": "savingImages/ios/stars.jpg" 
},
{
	 "categoryid": "0", "uri": "savingImages/ios/station.jpg" 
},
{
	 "categoryid": "0", "uri": "savingImages/ios/stump.jpg" 
},
{
	 "categoryid": "0", "uri": "savingImages/ios/suddenlyShanghai.jpg" 
},
{
	 "categoryid": "0", "uri": "savingImages/ios/summerBikes.jpg" 
},
{
	 "categoryid": "0", "uri": "savingImages/ios/sunGrass.jpg" 
},
{
	 "categoryid": "0", "uri": "savingImages/ios/sunlightParisAvenue.jpg" 
},
{
	 "categoryid": "0", "uri": "savingImages/ios/sunsetHair.jpg" 
},
{
	 "categoryid": "0", "uri": "savingImages/ios/sunsetMyCity.jpg" 
},
{
	 "categoryid": "0", "uri": "savingImages/ios/sunsetTrees.jpg" 
},
{
	 "categoryid": "0", "uri": "savingImages/ios/surf.jpg" 
},
{
	 "categoryid": "0", "uri": "savingImages/ios/surfMist.jpg" 
},
{
	 "categoryid": "0", "uri": "savingImages/ios/susans.jpg" 
},
{
	 "categoryid": "0", "uri": "savingImages/ios/tarmac.jpg" 
},
{
	 "categoryid": "0", "uri": "savingImages/ios/tea.jpg" 
},
{
	 "categoryid": "0", "uri": "savingImages/ios/terraceStreet.jpg" 
},
{
	 "categoryid": "0", "uri": "savingImages/ios/thailand.jpg" 
},
{
	 "categoryid": "0", "uri": "savingImages/ios/thanks.jpg" 
},
{
	 "categoryid": "0", "uri": "savingImages/ios/theBearIsHungry.jpg" 
},
{
	 "categoryid": "0", "uri": "savingImages/ios/threeCanoes.jpg" 
},
{
	 "categoryid": "0", "uri": "savingImages/ios/tiffanyBug.jpg" 
},
{
	 "categoryid": "0", "uri": "savingImages/ios/timesSquare.jpg" 
},
{
	 "categoryid": "0", "uri": "savingImages/ios/track.jpg" 
},
{
	 "categoryid": "0", "uri": "savingImages/ios/traffic.jpg" 
},
{
	 "categoryid": "0", "uri": "savingImages/ios/tree.jpg" 
},
{
	 "categoryid": "0", "uri": "savingImages/ios/tuscany.jpg" 
},
{
	 "categoryid": "0", "uri": "savingImages/ios/typewriterTime.jpg" 
},
{
	 "categoryid": "0", "uri": "savingImages/ios/ukStreet.jpg" 
},
{
	 "categoryid": "0", "uri": "savingImages/ios/uluru.jpg" 
},
{
	 "categoryid": "0", "uri": "savingImages/ios/vatican.jpg" 
},
{
	 "categoryid": "0", "uri": "savingImages/ios/veniceHill.jpg" 
},
{
	 "categoryid": "0", "uri": "savingImages/ios/wake.jpg" 
},
{
	 "categoryid": "0", "uri": "savingImages/ios/waterfallBig.jpg" 
},
{
	 "categoryid": "0", "uri": "savingImages/ios/waterWood.jpg" 
},
{
	 "categoryid": "0", "uri": "savingImages/ios/wetPuppyFloppyEars.jpg" 
},
{
	 "categoryid": "0", "uri": "savingImages/ios/whiteSandsRoad.jpg" 
},
{
	 "categoryid": "0", "uri": "savingImages/ios/wideBeach.jpg" 
},
{
	 "categoryid": "0", "uri": "savingImages/ios/wideRiverDeltaLight1.jpg" 
},
{
	 "categoryid": "0", "uri": "savingImages/ios/wideRiverDeltaLight2.jpg" 
},
{
	 "categoryid": "0", "uri": "savingImages/ios/windowDroplet.jpg" 
},
{
	 "categoryid": "0", "uri": "savingImages/ios/windowpane.jpg" 
},
{
	 "categoryid": "0", "uri": "savingImages/ios/woodPile.jpg" 
},
{
	 "categoryid": "0", "uri": "savingImages/ios/work.jpg" 
},
{
	 "categoryid": "0", "uri": "savingImages/ios/yacht.jpg" 
},
{
	 "categoryid": "0", "uri": "savingImages/ios/yeah.jpg" 
},
{
	 "categoryid": "0", "uri": "savingImages/ios/yoKnowWhatItIs.jpg" 
},
{
	 "categoryid": "0", "uri": "savingImages/ios/yosemiteGlow.jpg" 
}
 ] }